YOMAPI
