Metadata-Version: 2.1
Name: YOMAPIClient
Version: 0.1.21
Summary: A PACKAGE TO USE THE SAME YOM API INTERFACE FROM YOM INTEGRATIONS
Home-page: https://github.com/YOMCL/yom-pylib-api-client
Author: Carlos Fuentes
Author-email: carlos@yom.ai
License: MIT
Keywords: YOM-INTEGRATIONS
Classifier: Development Status :: 3 - Alpha
Classifier: Intended Audience :: Developers
Classifier: Topic :: Software Development :: Build Tools
Classifier: License :: OSI Approved :: MIT License
Classifier: Programming Language :: Python :: 3.6
Classifier: Programming Language :: Python :: 3.7
Classifier: Programming Language :: Python :: 3.8
Classifier: Programming Language :: Python :: 3.9
Requires-Python: >=3.6
License-File: LICENSE.txt
